gigabloat/__init__.py
gigabloat/__main__.py
gigabloat/coverter/convert.py
gigabloat/gatherer/__init__.py
gigabloat/gatherer/categories.py
gigabloat/gatherer/commands.py
gigabloat/gatherer/directory.py
gigabloat/gatherer/file.py
gigabloat/gatherer/report.py
gigabloat/gatherer/scanner.py
gigabloat-0.1.3.dist-info/LICENSE
gigabloat-0.1.3.dist-info/WHEEL
gigabloat-0.1.3.dist-info/METADATA
gigabloat-0.1.3.dist-info/RECORD
