Metadata-Version: 2.1
Name: gigabloat
Version: 0.1.3
Summary: Tool to get general file and directory stats
Home-page: https://github.com/ArtemKolichenkov/gigabloat_scanner
License: GPL-3.0-or-later
Keywords: bloat,filemanager
Author: Artem Kolichenkov
Author-email: artem@kolichenkov.com
Requires-Python: >=3.8.2,<4.0.0
Classifier: License :: OSI Approved :: GNU General Public License v3 or later (GPLv3+)
Classifier: Programming Language :: Python :: 3
Requires-Dist: click (>=7.1.2,<8.0.0)
Requires-Dist: humanize (>=2.4.0,<3.0.0)
Requires-Dist: tabulate (>=0.8.7,<0.9.0)
Project-URL: Repository, https://github.com/ArtemKolichenkov/gigabloat_scanner
Project-URL: Tracker, https://github.com/ArtemKolichenkov/gigabloat_scanner/issues
